OTCFinUtils/__init__.py
OTCFinUtils/buffer.py
OTCFinUtils/data_structs.py
OTCFinUtils/dataverse_handler.py
OTCFinUtils/mapper.py
OTCFinUtils/mapper_loading.py
OTCFinUtils/security.py
OTCFinUtils/sharepoint.py
OTCFinUtils/utils.py
OTCFinUtils_0.0.1-0.0.1.0.dist-info/METADATA
OTCFinUtils_0.0.1-0.0.1.0.dist-info/WHEEL
OTCFinUtils_0.0.1-0.0.1.0.dist-info/top_level.txt
OTCFinUtils_0.0.1-0.0.1.0.dist-info/RECORD
