Metadata-Version: 2.1
Name: OTCFinUtils_0.0.1
Version: 0.0.1.0
Summary: usefule functions to iteract with dataverse and sharepoint
Author-email: saldujaily@otcfin.com
